<bill session="114" type="h" number="5617" updated="2017-06-02T22:09:39Z">
  <state datetime="2016-07-01">REFERRED</state>
  <status>
    <introduced datetime="2016-07-01"/>
  </status>
  <introduced datetime="2016-07-01"/>
  <titles>
    <title type="short" as="introduced">Underwater Student Borrowers Act</title>
    <title type="official" as="introduced">To amend the Internal Revenue Code of 1986 to exclude from gross income any discharge of student loan indebtedness.</title>
    <title type="display">Underwater Student Borrowers Act</title>
  </titles>
  <sponsor id="412585"/>
  <cosponsors>
    <cosponsor id="412501" joined="2016-07-01"/>
    <cosponsor id="412652" joined="2016-07-05"/>
    <cosponsor id="400100" joined="2016-07-01"/>
    <cosponsor id="412215" joined="2016-07-01"/>
    <cosponsor id="400162" joined="2016-07-01"/>
    <cosponsor id="400179" joined="2016-07-01"/>
    <cosponsor id="400199" joined="2016-07-08"/>
    <cosponsor id="400262" joined="2016-07-01"/>
    <cosponsor id="400263" joined="2016-07-01"/>
    <cosponsor id="412189" joined="2016-07-18"/>
    <cosponsor id="400661" joined="2016-07-01"/>
    <cosponsor id="408211" joined="2016-07-01"/>
    <cosponsor id="400295" joined="2016-07-01"/>
    <cosponsor id="400333" joined="2016-07-08"/>
    <cosponsor id="412212" joined="2016-07-01"/>
    <cosponsor id="400364" joined="2016-07-01"/>
    <cosponsor id="412520" joined="2016-07-01"/>
    <cosponsor id="400415" joined="2016-07-08"/>
    <cosponsor id="400416" joined="2016-07-01"/>
    <cosponsor id="412412" joined="2016-07-01"/>
  </cosponsors>
  <actions>
    <action datetime="2016-07-01">
      <text>Introduced in House</text>
    </action>
    <action datetime="2016-07-01" state="REFERRED">
      <text>Referred to the House Committee on Ways and Means.</text>
    </action>
  </actions>
  <committees>
    <committee code="HSWM" name="House Ways and Means" activity="Referral"/>
  </committees>
  <relatedbills>
    <bill relation="unknown" session="114" type="h" number="2429"/>
  </relatedbills>
  <subjects>
    <term name="Taxation"/>
    <term name="Government lending and loan guarantees"/>
    <term name="Higher education"/>
    <term name="Income tax exclusion"/>
    <term name="Student aid and college costs"/>
  </subjects>
  <amendments/>
  <summary date="2016-07-01T04:00:00Z" status="Introduced in House">Underwater Student Borrowers Act

This bill amends the Internal Revenue Code, with respect to the exclusion from gross income of income attributable to the discharge of student loan indebtedness, to: (1) include indebtedness discharged due to income-contingent and income-based repayment plans, the death or disability of the borrower, or the closing of an educational institution; and (2)&#160;revise the definition of "student loan" to&#160;mean a loan made by any lender, including a loan for the refinancing of an existing loan.</summary>
  <committee-reports/>
</bill>
