<?xml version="1.0" encoding="UTF-8"?>
<billStatus>
  <bill>
    <billType>HR</billType>
    <updateDate>2017-06-02T21:36:11Z</updateDate>
    <subjects>
      <billSubjects>
        <legislativeSubjects>
          <item>
            <name>Alternative dispute resolution, mediation, arbitration</name>
          </item>
          <item>
            <name>Building construction</name>
          </item>
          <item>
            <name>Civil actions and liability</name>
          </item>
          <item>
            <name>Disability and health-based discrimination</name>
          </item>
          <item>
            <name>State and local government operations</name>
          </item>
        </legislativeSubjects>
        <policyArea>
          <name>Civil Rights and Liberties, Minority Issues</name>
        </policyArea>
      </billSubjects>
    </subjects>
    <policyArea>
      <name>Civil Rights and Liberties, Minority Issues</name>
    </policyArea>
    <laws />
    <version>1.0.0</version>
    <amendments />
    <calendarNumbers />
    <relatedBills>
      <item>
        <type>S</type>
        <latestAction>
          <text>Read twice and referred to the Committee on the Judiciary.</text>
          <actionDate>2016-09-28</actionDate>
        </latestAction>
        <congress>114</congress>
        <number>3446</number>
        <latestTitle>ADA Education and Reform Act of 2016</latestTitle>
        <relationshipDetails>
          <item>
            <type>Related bill</type>
            <identifiedBy>CRS</identifiedBy>
          </item>
        </relationshipDetails>
      </item>
    </relatedBills>
    <introducedDate>2015-10-20</introducedDate>
    <notes />
    <latestAction>
      <text>Ordered to be Reported (Amended) by the Yeas and Nays: 15 - 6.</text>
      <actionDate>2016-07-07</actionDate>
      <links />
    </latestAction>
    <originChamber>House</originChamber>
    <sponsors>
      <item>
        <lastName>Poe</lastName>
        <identifiers>
          <gpoId>8158</gpoId>
          <bioguideId>P000592</bioguideId>
          <lisID>1802</lisID>
        </identifiers>
        <firstName>Ted</firstName>
        <bioguideId>P000592</bioguideId>
        <middleName />
        <byRequestType />
        <state>TX</state>
        <district>2</district>
        <party>R</party>
        <fullName>Rep. Poe, Ted [R-TX-2]</fullName>
      </item>
    </sponsors>
    <recordedVotes />
    <billNumber>3765</billNumber>
    <titles>
      <item>
        <chamberName />
        <parentTitleType />
        <title>ADA Education and Reform Act of 2015</title>
        <chamberCode />
        <titleType>Short Titles as Introduced</titleType>
      </item>
      <item>
        <chamberName />
        <parentTitleType />
        <title>To amend the Americans with Disabilities Act of 1990 to promote compliance through education, to clarify the requirements for demand letters, to provide for a notice and cure period before the commencement of a private civil action, and for other purposes.</title>
        <chamberCode />
        <titleType>Official Title as Introduced</titleType>
      </item>
      <item>
        <chamberName />
        <parentTitleType />
        <title>ADA Education and Reform Act of 2015</title>
        <chamberCode />
        <titleType>Display Title</titleType>
      </item>
    </titles>
    <summaries>
      <billSummaries>
        <item>
          <lastSummaryUpdateDate>2015-11-30T20:06:57Z</lastSummaryUpdateDate>
          <updateDate>2015-10-20T04:00:00Z</updateDate>
          <versionCode>00</versionCode>
          <actionDate>2015-10-20</actionDate>
          <name>Introduced in House</name>
          <actionDesc>Introduced in House</actionDesc>
          <text><![CDATA[<p><b>ADA Education and Reform Act of 2015</b></p> <p>This bill requires the Disability Rights Section of the Department of Justice to develop a program to educate state and local governments and property owners on strategies for promoting access to public accommodations for persons with a disability. The program may include training for professionals to provide a guidance of remediation for potential violations of the Americans with Disabilities Act of 1990 (ADA).</p> <p>The bill prohibits persons from, and subjects violators to a criminal fine for, sending demand letters or other pre-suit notifications alleging a violation of ADA public accommodation requirements if the notification does not specify the circumstances under which an individual was actually denied access. The notification must specify: (1) the address of property, (2) the specific ADA sections alleged to have been violated, (3) whether a request for assistance in removing an architectural barrier was made, and (4) whether the barrier was permanent or temporary. </p> <p>The bill also prohibits commencement of civil action based on the failure to remove an architectural barrier to access into an existing public accommodation unless: (1) the aggrieved person has provided to the owners or operators a written notice specific enough to identify the barrier, and (2) the owners or operators fail to provide the person with a written description outlining improvements that will be made to improve the barrier or they fail to remove the barrier or make substantial progress after providing such a description.</p> <p>The Judicial Conference of the United States must develop a model program to promote alternative dispute resolution mechanisms to resolve such claims. The model program should include an expedited method for determining relevant facts related to such barriers and steps to resolve accessibility issues before litigation.</p>]]></text>
        </item>
      </billSummaries>
    </summaries>
    <congress>114</congress>
    <committeeReports />
    <title>ADA Education and Reform Act of 2015</title>
    <cboCostEstimates>
      <item>
        <pubDate>2016-10-21T20:47:00Z</pubDate>
        <title>H.R. 3765, ADA Education and Reform Act of 2016</title>
        <url>https://www.cbo.gov/publication/52131</url>
      </item>
    </cboCostEstimates>
    <actions>
      <actionTypeCounts>
        <placeholderTextForH>3</placeholderTextForH>
        <billReferrals>1</billReferrals>
        <placeholderTextForB>1</placeholderTextForB>
        <actionStageOverride>1</actionStageOverride>
        <introducedInHouse>1</introducedInHouse>
        <introducedInTheHouse>1</introducedInTheHouse>
      </actionTypeCounts>
      <item>
        <actionDate>2016-07-07</actionDate>
        <committee>
          <name>Judiciary Committee</name>
          <systemCode>hsju00</systemCode>
        </committee>
        <links />
        <sourceSystem>
          <code>1</code>
          <name>House committee actions</name>
        </sourceSystem>
        <text>Ordered to be Reported (Amended) by the Yeas and Nays: 15 - 6.</text>
        <type>Committee</type>
      </item>
      <item>
        <actionDate>2016-07-07</actionDate>
        <committee>
          <name>Judiciary Committee</name>
          <systemCode>hsju00</systemCode>
        </committee>
        <links />
        <sourceSystem>
          <code>1</code>
          <name>House committee actions</name>
        </sourceSystem>
        <text>Committee Consideration and Mark-up Session Held.</text>
        <type>Committee</type>
      </item>
      <item>
        <actionDate>2016-07-05</actionDate>
        <committee>
          <name>Judiciary Committee</name>
          <systemCode>hsju00</systemCode>
        </committee>
        <links />
        <sourceSystem>
          <code>1</code>
          <name>House committee actions</name>
        </sourceSystem>
        <text>Subcommittee on the Constitution and Civil Justice Discharged.</text>
        <type>Committee</type>
      </item>
      <item>
        <actionDate>2015-11-03</actionDate>
        <committee>
          <name>Constitution and Civil Justice Subcommittee</name>
          <systemCode>hsju10</systemCode>
        </committee>
        <links />
        <sourceSystem>
          <code>1</code>
          <name>House committee actions</name>
        </sourceSystem>
        <text>Referred to the Subcommittee on the Constitution and Civil Justice.</text>
        <type>Committee</type>
      </item>
      <item>
        <links>
          <link>
            <name>H7393-7394</name>
            <url>https://www.congress.gov/congressional-record/volume-161/house-section/page/H7393-7394</url>
          </link>
        </links>
        <actionDate>2015-11-03</actionDate>
        <text>Sponsor introductory remarks on measure. (CR H7393-7394)</text>
        <sourceSystem>
          <code>9</code>
          <name>Library of Congress</name>
        </sourceSystem>
        <actionCode>B00100</actionCode>
        <type>IntroReferral</type>
        <committee />
      </item>
      <item>
        <links />
        <actionDate>2015-10-20</actionDate>
        <text>Referred to the House Committee on the Judiciary.</text>
        <sourceSystem>
          <code>2</code>
          <name>House floor actions</name>
        </sourceSystem>
        <actionCode>H11100</actionCode>
        <type>IntroReferral</type>
        <committee>
          <name>Judiciary Committee</name>
          <systemCode>hsju00</systemCode>
        </committee>
      </item>
      <item>
        <links />
        <actionDate>2015-10-20</actionDate>
        <text>Introduced in House</text>
        <sourceSystem>
          <code>9</code>
          <name>Library of Congress</name>
        </sourceSystem>
        <actionCode>Intro-H</actionCode>
        <type>IntroReferral</type>
        <committee />
      </item>
      <item>
        <links />
        <actionDate>2015-10-20</actionDate>
        <text>Introduced in House</text>
        <sourceSystem>
          <code>9</code>
          <name>Library of Congress</name>
        </sourceSystem>
        <actionCode>1000</actionCode>
        <type>IntroReferral</type>
        <committee />
      </item>
      <actionByCounts>
        <houseOfRepresentatives>7</houseOfRepresentatives>
      </actionByCounts>
    </actions>
    <createDate>2015-10-21T09:20:41Z</createDate>
    <cosponsors>
      <item>
        <state>GA</state>
        <identifiers>
          <lisID>2121</lisID>
          <gpoId />
          <bioguideId>C001093</bioguideId>
        </identifiers>
        <firstName>Doug</firstName>
        <isOriginalCosponsor>True</isOriginalCosponsor>
        <fullName>Rep. Collins, Doug [R-GA-9]</fullName>
        <sponsorshipDate>2015-10-20</sponsorshipDate>
        <district>9</district>
        <middleName />
        <sponsorshipWithdrawnDate />
        <lastName>Collins</lastName>
        <bioguideId>C001093</bioguideId>
        <party>R</party>
      </item>
      <item>
        <state>FL</state>
        <identifiers>
          <gpoId />
          <bioguideId>J000296</bioguideId>
          <lisID>2199</lisID>
        </identifiers>
        <firstName>David</firstName>
        <isOriginalCosponsor>True</isOriginalCosponsor>
        <fullName>Rep. Jolly, David [R-FL-13]</fullName>
        <sponsorshipDate>2015-10-20</sponsorshipDate>
        <district>13</district>
        <middleName>W.</middleName>
        <sponsorshipWithdrawnDate>2016-05-24</sponsorshipWithdrawnDate>
        <lastName>Jolly</lastName>
        <bioguideId>J000296</bioguideId>
        <party>R</party>
      </item>
      <item>
        <state>TX</state>
        <identifiers>
          <lisID>1806</lisID>
          <gpoId>8766</gpoId>
          <bioguideId>M001158</bioguideId>
        </identifiers>
        <firstName>Kenny</firstName>
        <isOriginalCosponsor>False</isOriginalCosponsor>
        <fullName>Rep. Marchant, Kenny [R-TX-24]</fullName>
        <sponsorshipDate>2015-10-23</sponsorshipDate>
        <district>24</district>
        <middleName />
        <sponsorshipWithdrawnDate />
        <lastName>Marchant</lastName>
        <bioguideId>M001158</bioguideId>
        <party>R</party>
      </item>
      <item>
        <state>TX</state>
        <identifiers>
          <gpoId>8177</gpoId>
          <bioguideId>S000583</bioguideId>
          <lisID>1075</lisID>
        </identifiers>
        <firstName>LAMAR</firstName>
        <isOriginalCosponsor>False</isOriginalCosponsor>
        <fullName>Rep. Smith, Lamar [R-TX-21]</fullName>
        <sponsorshipDate>2015-10-23</sponsorshipDate>
        <district>21</district>
        <middleName />
        <sponsorshipWithdrawnDate />
        <lastName>SMITH</lastName>
        <bioguideId>S000583</bioguideId>
        <party>R</party>
      </item>
      <item>
        <state>SC</state>
        <identifiers>
          <bioguideId>M001182</bioguideId>
          <gpoId>8145</gpoId>
          <lisID>2059</lisID>
        </identifiers>
        <firstName>Mick</firstName>
        <isOriginalCosponsor>False</isOriginalCosponsor>
        <fullName>Rep. Mulvaney, Mick [R-SC-5]</fullName>
        <sponsorshipDate>2015-10-28</sponsorshipDate>
        <district>5</district>
        <middleName />
        <sponsorshipWithdrawnDate />
        <lastName>Mulvaney</lastName>
        <bioguideId>M001182</bioguideId>
        <party>R</party>
      </item>
      <item>
        <state>CA</state>
        <identifiers>
          <lisID>1710</lisID>
          <bioguideId>N000181</bioguideId>
          <gpoId>7826</gpoId>
        </identifiers>
        <firstName>Devin</firstName>
        <isOriginalCosponsor>False</isOriginalCosponsor>
        <fullName>Rep. Nunes, Devin [R-CA-22]</fullName>
        <sponsorshipDate>2015-11-02</sponsorshipDate>
        <district>22</district>
        <middleName />
        <sponsorshipWithdrawnDate />
        <lastName>Nunes</lastName>
        <bioguideId>N000181</bioguideId>
        <party>R</party>
      </item>
      <item>
        <state>CA</state>
        <identifiers>
          <gpoId>7824</gpoId>
          <bioguideId>D000612</bioguideId>
          <lisID>1995</lisID>
        </identifiers>
        <firstName>Jeff</firstName>
        <isOriginalCosponsor>False</isOriginalCosponsor>
        <fullName>Rep. Denham, Jeff [R-CA-10]</fullName>
        <sponsorshipDate>2015-11-16</sponsorshipDate>
        <district>10</district>
        <middleName />
        <sponsorshipWithdrawnDate />
        <lastName>Denham</lastName>
        <bioguideId>D000612</bioguideId>
        <party>R</party>
      </item>
      <item>
        <state>TX</state>
        <identifiers>
          <lisID>2270</lisID>
          <gpoId />
          <bioguideId>B001291</bioguideId>
        </identifiers>
        <firstName>Brian</firstName>
        <isOriginalCosponsor>False</isOriginalCosponsor>
        <fullName>Rep. Babin, Brian [R-TX-36]</fullName>
        <sponsorshipDate>2015-11-17</sponsorshipDate>
        <district>36</district>
        <middleName />
        <sponsorshipWithdrawnDate />
        <lastName>Babin</lastName>
        <bioguideId>B001291</bioguideId>
        <party>R</party>
      </item>
      <item>
        <state>AL</state>
        <identifiers>
          <lisID>2197</lisID>
          <gpoId />
          <bioguideId>B001289</bioguideId>
        </identifiers>
        <firstName>Bradley</firstName>
        <isOriginalCosponsor>False</isOriginalCosponsor>
        <fullName>Rep. Byrne, Bradley [R-AL-1]</fullName>
        <sponsorshipDate>2015-11-17</sponsorshipDate>
        <district>1</district>
        <middleName />
        <sponsorshipWithdrawnDate />
        <lastName>Byrne</lastName>
        <bioguideId>B001289</bioguideId>
        <party>R</party>
      </item>
      <item>
        <state>CA</state>
        <identifiers>
          <lisID>2105</lisID>
          <bioguideId>V000129</bioguideId>
          <gpoId />
        </identifiers>
        <firstName>David</firstName>
        <isOriginalCosponsor>False</isOriginalCosponsor>
        <fullName>Rep. Valadao, David G. [R-CA-21]</fullName>
        <sponsorshipDate>2015-11-18</sponsorshipDate>
        <district>21</district>
        <middleName>G.</middleName>
        <sponsorshipWithdrawnDate />
        <lastName>Valadao</lastName>
        <bioguideId>V000129</bioguideId>
        <party>R</party>
      </item>
      <item>
        <state>TX</state>
        <identifiers>
          <gpoId>8182</gpoId>
          <bioguideId>B001248</bioguideId>
          <lisID>1751</lisID>
        </identifiers>
        <firstName>Michael</firstName>
        <isOriginalCosponsor>False</isOriginalCosponsor>
        <fullName>Rep. Burgess, Michael C. [R-TX-26]</fullName>
        <sponsorshipDate>2015-11-19</sponsorshipDate>
        <district>26</district>
        <middleName>C.</middleName>
        <sponsorshipWithdrawnDate />
        <lastName>Burgess</lastName>
        <bioguideId>B001248</bioguideId>
        <party>R</party>
      </item>
      <item>
        <state>FL</state>
        <identifiers>
          <lisID>985</lisID>
          <gpoId>7890</gpoId>
          <bioguideId>R000435</bioguideId>
        </identifiers>
        <firstName>ILEANA</firstName>
        <isOriginalCosponsor>False</isOriginalCosponsor>
        <fullName>Rep. Ros-Lehtinen, Ileana [R-FL-27]</fullName>
        <sponsorshipDate>2015-11-30</sponsorshipDate>
        <district>27</district>
        <middleName />
        <sponsorshipWithdrawnDate />
        <lastName>ROS-LEHTINEN</lastName>
        <bioguideId>R000435</bioguideId>
        <party>R</party>
      </item>
      <item>
        <state>AZ</state>
        <identifiers>
          <lisID>1994</lisID>
          <gpoId>7802</gpoId>
          <bioguideId>S001183</bioguideId>
        </identifiers>
        <firstName>David</firstName>
        <isOriginalCosponsor>False</isOriginalCosponsor>
        <fullName>Rep. Schweikert, David [R-AZ-6]</fullName>
        <sponsorshipDate>2015-12-01</sponsorshipDate>
        <district>6</district>
        <middleName />
        <sponsorshipWithdrawnDate />
        <lastName>Schweikert</lastName>
        <bioguideId>S001183</bioguideId>
        <party>R</party>
      </item>
      <item>
        <state>CA</state>
        <identifiers>
          <gpoId />
          <bioguideId>P000608</bioguideId>
          <lisID>2113</lisID>
        </identifiers>
        <firstName>Scott</firstName>
        <isOriginalCosponsor>False</isOriginalCosponsor>
        <fullName>Rep. Peters, Scott H. [D-CA-52]</fullName>
        <sponsorshipDate>2016-01-05</sponsorshipDate>
        <district>52</district>
        <middleName>H.</middleName>
        <sponsorshipWithdrawnDate />
        <lastName>Peters</lastName>
        <bioguideId>P000608</bioguideId>
        <party>D</party>
      </item>
      <item>
        <state>MN</state>
        <identifiers>
          <lisID>2253</lisID>
          <bioguideId>E000294</bioguideId>
          <gpoId />
        </identifiers>
        <firstName>Tom</firstName>
        <isOriginalCosponsor>False</isOriginalCosponsor>
        <fullName>Rep. Emmer, Tom [R-MN-6]</fullName>
        <sponsorshipDate>2016-01-05</sponsorshipDate>
        <district>6</district>
        <middleName />
        <sponsorshipWithdrawnDate />
        <lastName>Emmer</lastName>
        <bioguideId>E000294</bioguideId>
        <party>R</party>
      </item>
      <item>
        <state>OK</state>
        <identifiers>
          <lisID>1742</lisID>
          <gpoId>8112</gpoId>
          <bioguideId>C001053</bioguideId>
        </identifiers>
        <firstName>Tom</firstName>
        <isOriginalCosponsor>False</isOriginalCosponsor>
        <fullName>Rep. Cole, Tom [R-OK-4]</fullName>
        <sponsorshipDate>2016-01-13</sponsorshipDate>
        <district>4</district>
        <middleName />
        <sponsorshipWithdrawnDate />
        <lastName>Cole</lastName>
        <bioguideId>C001053</bioguideId>
        <party>R</party>
      </item>
      <item>
        <state>NY</state>
        <identifiers>
          <bioguideId>R000053</bioguideId>
          <gpoId>8076</gpoId>
          <lisID>944</lisID>
        </identifiers>
        <firstName>CHARLES</firstName>
        <isOriginalCosponsor>False</isOriginalCosponsor>
        <fullName>Rep. Rangel, Charles B. [D-NY-13]</fullName>
        <sponsorshipDate>2016-02-03</sponsorshipDate>
        <district>13</district>
        <middleName>B.</middleName>
        <sponsorshipWithdrawnDate>2016-09-14</sponsorshipWithdrawnDate>
        <lastName>RANGEL</lastName>
        <bioguideId>R000053</bioguideId>
        <party>D</party>
      </item>
      <item>
        <state>TX</state>
        <identifiers>
          <gpoId>8178</gpoId>
          <bioguideId>O000168</bioguideId>
          <lisID>1955</lisID>
        </identifiers>
        <firstName>Pete</firstName>
        <isOriginalCosponsor>False</isOriginalCosponsor>
        <fullName>Rep. Olson, Pete [R-TX-22]</fullName>
        <sponsorshipDate>2016-02-04</sponsorshipDate>
        <district>22</district>
        <middleName />
        <sponsorshipWithdrawnDate />
        <lastName>Olson</lastName>
        <bioguideId>O000168</bioguideId>
        <party>R</party>
      </item>
      <item>
        <state>NV</state>
        <identifiers>
          <lisID>2090</lisID>
          <gpoId>8366</gpoId>
          <bioguideId>A000369</bioguideId>
        </identifiers>
        <firstName>Mark</firstName>
        <isOriginalCosponsor>False</isOriginalCosponsor>
        <fullName>Rep. Amodei, Mark E. [R-NV-2]</fullName>
        <sponsorshipDate>2016-02-11</sponsorshipDate>
        <district>2</district>
        <middleName>E.</middleName>
        <sponsorshipWithdrawnDate />
        <lastName>Amodei</lastName>
        <bioguideId>A000369</bioguideId>
        <party>R</party>
      </item>
      <item>
        <state>AL</state>
        <identifiers>
          <lisID>1704</lisID>
          <gpoId>7788</gpoId>
          <bioguideId>R000575</bioguideId>
        </identifiers>
        <firstName>Mike</firstName>
        <isOriginalCosponsor>False</isOriginalCosponsor>
        <fullName>Rep. Rogers, Mike D. [R-AL-3]</fullName>
        <sponsorshipDate>2016-02-12</sponsorshipDate>
        <district>3</district>
        <middleName />
        <sponsorshipWithdrawnDate />
        <lastName>Rogers</lastName>
        <bioguideId>R000575</bioguideId>
        <party>R</party>
      </item>
      <item>
        <state>TX</state>
        <identifiers>
          <lisID>1805</lisID>
          <gpoId>8167</gpoId>
          <bioguideId>C001062</bioguideId>
        </identifiers>
        <firstName>K.</firstName>
        <isOriginalCosponsor>False</isOriginalCosponsor>
        <fullName>Rep. Conaway, K. Michael [R-TX-11]</fullName>
        <sponsorshipDate>2016-02-12</sponsorshipDate>
        <district>11</district>
        <middleName>Michael</middleName>
        <sponsorshipWithdrawnDate />
        <lastName>Conaway</lastName>
        <bioguideId>C001062</bioguideId>
        <party>R</party>
      </item>
      <item>
        <state>TX</state>
        <identifiers>
          <lisID>1749</lisID>
          <bioguideId>H001036</bioguideId>
          <gpoId>8161</gpoId>
        </identifiers>
        <firstName>Jeb</firstName>
        <isOriginalCosponsor>False</isOriginalCosponsor>
        <fullName>Rep. Hensarling, Jeb [R-TX-5]</fullName>
        <sponsorshipDate>2016-02-25</sponsorshipDate>
        <district>5</district>
        <middleName />
        <sponsorshipWithdrawnDate />
        <lastName>Hensarling</lastName>
        <bioguideId>H001036</bioguideId>
        <party>R</party>
      </item>
      <item>
        <state>MO</state>
        <identifiers>
          <bioguideId>G000546</bioguideId>
          <gpoId>8014</gpoId>
          <lisID>1656</lisID>
        </identifiers>
        <firstName>SAM</firstName>
        <isOriginalCosponsor>False</isOriginalCosponsor>
        <fullName>Rep. Graves, Sam [R-MO-6]</fullName>
        <sponsorshipDate>2016-03-15</sponsorshipDate>
        <district>6</district>
        <middleName />
        <sponsorshipWithdrawnDate />
        <lastName>GRAVES</lastName>
        <bioguideId>G000546</bioguideId>
        <party>R</party>
      </item>
      <item>
        <state>NE</state>
        <identifiers>
          <lisID>2257</lisID>
          <gpoId />
          <bioguideId>A000373</bioguideId>
        </identifiers>
        <firstName>Brad</firstName>
        <isOriginalCosponsor>False</isOriginalCosponsor>
        <fullName>Rep. Ashford, Brad [D-NE-2]</fullName>
        <sponsorshipDate>2016-03-15</sponsorshipDate>
        <district>2</district>
        <middleName />
        <sponsorshipWithdrawnDate />
        <lastName>Ashford</lastName>
        <bioguideId>A000373</bioguideId>
        <party>D</party>
      </item>
      <item>
        <state>GA</state>
        <identifiers>
          <lisID>2236</lisID>
          <bioguideId>C001103</bioguideId>
          <gpoId />
        </identifiers>
        <firstName>Earl</firstName>
        <isOriginalCosponsor>False</isOriginalCosponsor>
        <fullName>Rep. Carter, Earl L. "Buddy" [R-GA-1]</fullName>
        <sponsorshipDate>2016-03-15</sponsorshipDate>
        <district>1</district>
        <middleName>L. "Buddy"</middleName>
        <sponsorshipWithdrawnDate />
        <lastName>Carter</lastName>
        <bioguideId>C001103</bioguideId>
        <party>R</party>
      </item>
      <item>
        <state>OK</state>
        <identifiers>
          <bioguideId>R000604</bioguideId>
          <gpoId />
          <lisID>2265</lisID>
        </identifiers>
        <firstName>Steve</firstName>
        <isOriginalCosponsor>False</isOriginalCosponsor>
        <fullName>Rep. Russell, Steve [R-OK-5]</fullName>
        <sponsorshipDate>2016-03-15</sponsorshipDate>
        <district>5</district>
        <middleName />
        <sponsorshipWithdrawnDate />
        <lastName>Russell</lastName>
        <bioguideId>R000604</bioguideId>
        <party>R</party>
      </item>
      <item>
        <state>TX</state>
        <identifiers>
          <lisID>603</lisID>
          <gpoId>8159</gpoId>
          <bioguideId>J000174</bioguideId>
        </identifiers>
        <firstName>SAM</firstName>
        <isOriginalCosponsor>False</isOriginalCosponsor>
        <fullName>Rep. Johnson, Sam [R-TX-3]</fullName>
        <sponsorshipDate>2016-04-13</sponsorshipDate>
        <district>3</district>
        <middleName />
        <sponsorshipWithdrawnDate />
        <lastName>JOHNSON</lastName>
        <bioguideId>J000174</bioguideId>
        <party>R</party>
      </item>
      <item>
        <state>MO</state>
        <identifiers>
          <bioguideId>L000569</bioguideId>
          <gpoId>8017</gpoId>
          <lisID>1931</lisID>
        </identifiers>
        <firstName>Blaine</firstName>
        <isOriginalCosponsor>False</isOriginalCosponsor>
        <fullName>Rep. Luetkemeyer, Blaine [R-MO-3]</fullName>
        <sponsorshipDate>2016-04-26</sponsorshipDate>
        <district>3</district>
        <middleName />
        <sponsorshipWithdrawnDate />
        <lastName>Luetkemeyer</lastName>
        <bioguideId>L000569</bioguideId>
        <party>R</party>
      </item>
      <item>
        <state>CO</state>
        <identifiers>
          <bioguideId>C001077</bioguideId>
          <gpoId>7864</gpoId>
          <lisID>1912</lisID>
        </identifiers>
        <firstName>Mike</firstName>
        <isOriginalCosponsor>False</isOriginalCosponsor>
        <fullName>Rep. Coffman, Mike [R-CO-6]</fullName>
        <sponsorshipDate>2016-04-26</sponsorshipDate>
        <district>6</district>
        <middleName />
        <sponsorshipWithdrawnDate />
        <lastName>Coffman</lastName>
        <bioguideId>C001077</bioguideId>
        <party>R</party>
      </item>
      <item>
        <state>CO</state>
        <identifiers>
          <lisID>2233</lisID>
          <bioguideId>B001297</bioguideId>
          <gpoId />
        </identifiers>
        <firstName>Ken</firstName>
        <isOriginalCosponsor>False</isOriginalCosponsor>
        <fullName>Rep. Buck, Ken [R-CO-4]</fullName>
        <sponsorshipDate>2016-04-26</sponsorshipDate>
        <district>4</district>
        <middleName />
        <sponsorshipWithdrawnDate />
        <lastName>Buck</lastName>
        <bioguideId>B001297</bioguideId>
        <party>R</party>
      </item>
      <item>
        <state>CA</state>
        <identifiers>
          <lisID>1890</lisID>
          <gpoId>7817</gpoId>
          <bioguideId>S001175</bioguideId>
        </identifiers>
        <firstName>Jackie</firstName>
        <isOriginalCosponsor>False</isOriginalCosponsor>
        <fullName>Rep. Speier, Jackie [D-CA-14]</fullName>
        <sponsorshipDate>2016-05-10</sponsorshipDate>
        <district>14</district>
        <middleName />
        <sponsorshipWithdrawnDate />
        <lastName>Speier</lastName>
        <bioguideId>S001175</bioguideId>
        <party>D</party>
      </item>
      <item>
        <state>TX</state>
        <identifiers>
          <lisID>1525</lisID>
          <gpoId>8188</gpoId>
          <bioguideId>S000250</bioguideId>
        </identifiers>
        <firstName>PETE</firstName>
        <isOriginalCosponsor>False</isOriginalCosponsor>
        <fullName>Rep. Sessions, Pete [R-TX-32]</fullName>
        <sponsorshipDate>2016-05-23</sponsorshipDate>
        <district>32</district>
        <middleName />
        <sponsorshipWithdrawnDate />
        <lastName>SESSIONS</lastName>
        <bioguideId>S000250</bioguideId>
        <party>R</party>
      </item>
      <item>
        <state>TX</state>
        <identifiers>
          <lisID>2165</lisID>
          <gpoId />
          <bioguideId>W000816</bioguideId>
        </identifiers>
        <firstName>Roger</firstName>
        <isOriginalCosponsor>False</isOriginalCosponsor>
        <fullName>Rep. Williams, Roger [R-TX-25]</fullName>
        <sponsorshipDate>2016-05-23</sponsorshipDate>
        <district>25</district>
        <middleName />
        <sponsorshipWithdrawnDate />
        <lastName>Williams</lastName>
        <bioguideId>W000816</bioguideId>
        <party>R</party>
      </item>
      <item>
        <state>NJ</state>
        <identifiers>
          <gpoId />
          <bioguideId>M001193</bioguideId>
          <lisID>2258</lisID>
        </identifiers>
        <firstName>Thomas</firstName>
        <isOriginalCosponsor>False</isOriginalCosponsor>
        <fullName>Rep. MacArthur, Thomas [R-NJ-3]</fullName>
        <sponsorshipDate>2016-05-27</sponsorshipDate>
        <district>3</district>
        <middleName />
        <sponsorshipWithdrawnDate />
        <lastName>MacArthur</lastName>
        <bioguideId>M001193</bioguideId>
        <party>R</party>
      </item>
      <item>
        <state>AL</state>
        <identifiers>
          <lisID>1460</lisID>
          <gpoId>7789</gpoId>
          <bioguideId>A000055</bioguideId>
        </identifiers>
        <firstName>ROBERT</firstName>
        <isOriginalCosponsor>False</isOriginalCosponsor>
        <fullName>Rep. Aderholt, Robert B. [R-AL-4]</fullName>
        <sponsorshipDate>2016-05-27</sponsorshipDate>
        <district>4</district>
        <middleName>B.</middleName>
        <sponsorshipWithdrawnDate />
        <lastName>ADERHOLT</lastName>
        <bioguideId>A000055</bioguideId>
        <party>R</party>
      </item>
      <item>
        <state>OR</state>
        <identifiers>
          <lisID>1596</lisID>
          <gpoId>8115</gpoId>
          <bioguideId>W000791</bioguideId>
        </identifiers>
        <firstName>GREG</firstName>
        <isOriginalCosponsor>False</isOriginalCosponsor>
        <fullName>Rep. Walden, Greg [R-OR-2]</fullName>
        <sponsorshipDate>2016-05-27</sponsorshipDate>
        <district>2</district>
        <middleName />
        <sponsorshipWithdrawnDate />
        <lastName>WALDEN</lastName>
        <bioguideId>W000791</bioguideId>
        <party>R</party>
      </item>
      <item>
        <state>CA</state>
        <identifiers>
          <lisID>1908</lisID>
          <gpoId>7809</gpoId>
          <bioguideId>M001177</bioguideId>
        </identifiers>
        <firstName>Tom</firstName>
        <isOriginalCosponsor>False</isOriginalCosponsor>
        <fullName>Rep. McClintock, Tom [R-CA-4]</fullName>
        <sponsorshipDate>2016-06-07</sponsorshipDate>
        <district>4</district>
        <middleName />
        <sponsorshipWithdrawnDate />
        <lastName>McClintock</lastName>
        <bioguideId>M001177</bioguideId>
        <party>R</party>
      </item>
      <item>
        <state>OK</state>
        <identifiers>
          <lisID>711</lisID>
          <bioguideId>L000491</bioguideId>
          <gpoId>8111</gpoId>
        </identifiers>
        <firstName>FRANK</firstName>
        <isOriginalCosponsor>False</isOriginalCosponsor>
        <fullName>Rep. Lucas, Frank D. [R-OK-3]</fullName>
        <sponsorshipDate>2016-06-08</sponsorshipDate>
        <district>3</district>
        <middleName>D.</middleName>
        <sponsorshipWithdrawnDate />
        <lastName>LUCAS</lastName>
        <bioguideId>L000491</bioguideId>
        <party>R</party>
      </item>
      <item>
        <state>WI</state>
        <identifiers>
          <gpoId />
          <bioguideId>G000576</bioguideId>
          <lisID>2276</lisID>
        </identifiers>
        <firstName>Glenn</firstName>
        <isOriginalCosponsor>False</isOriginalCosponsor>
        <fullName>Rep. Grothman, Glenn [R-WI-6]</fullName>
        <sponsorshipDate>2016-06-09</sponsorshipDate>
        <district>6</district>
        <middleName />
        <sponsorshipWithdrawnDate />
        <lastName>Grothman</lastName>
        <bioguideId>G000576</bioguideId>
        <party>R</party>
      </item>
      <item>
        <state>TX</state>
        <identifiers>
          <lisID>1801</lisID>
          <bioguideId>G000552</bioguideId>
          <gpoId>8157</gpoId>
        </identifiers>
        <firstName>Louie</firstName>
        <isOriginalCosponsor>False</isOriginalCosponsor>
        <fullName>Rep. Gohmert, Louie [R-TX-1]</fullName>
        <sponsorshipDate>2016-06-10</sponsorshipDate>
        <district>1</district>
        <middleName />
        <sponsorshipWithdrawnDate />
        <lastName>Gohmert</lastName>
        <bioguideId>G000552</bioguideId>
        <party>R</party>
      </item>
      <item>
        <state>CA</state>
        <identifiers>
          <bioguideId>I000056</bioguideId>
          <gpoId>7854</gpoId>
          <lisID>1640</lisID>
        </identifiers>
        <firstName>DARRELL</firstName>
        <isOriginalCosponsor>False</isOriginalCosponsor>
        <fullName>Rep. Issa, Darrell E. [R-CA-49]</fullName>
        <sponsorshipDate>2016-06-14</sponsorshipDate>
        <district>49</district>
        <middleName>E.</middleName>
        <sponsorshipWithdrawnDate />
        <lastName>ISSA</lastName>
        <bioguideId>I000056</bioguideId>
        <party>R</party>
      </item>
      <item>
        <state>CA</state>
        <identifiers>
          <lisID>2232</lisID>
          <gpoId />
          <bioguideId>W000820</bioguideId>
        </identifiers>
        <firstName>Mimi</firstName>
        <isOriginalCosponsor>False</isOriginalCosponsor>
        <fullName>Rep. Walters, Mimi [R-CA-45]</fullName>
        <sponsorshipDate>2016-06-14</sponsorshipDate>
        <district>45</district>
        <middleName />
        <sponsorshipWithdrawnDate />
        <lastName>Walters</lastName>
        <bioguideId>W000820</bioguideId>
        <party>R</party>
      </item>
      <item>
        <state>NC</state>
        <identifiers>
          <gpoId />
          <bioguideId>H001065</bioguideId>
          <lisID>2143</lisID>
        </identifiers>
        <firstName>George</firstName>
        <isOriginalCosponsor>False</isOriginalCosponsor>
        <fullName>Rep. Holding, George [R-NC-13]</fullName>
        <sponsorshipDate>2016-06-14</sponsorshipDate>
        <district>13</district>
        <middleName />
        <sponsorshipWithdrawnDate />
        <lastName>Holding</lastName>
        <bioguideId>H001065</bioguideId>
        <party>R</party>
      </item>
      <item>
        <state>PA</state>
        <identifiers>
          <lisID>1797</lisID>
          <bioguideId>F000451</bioguideId>
          <gpoId>8126</gpoId>
        </identifiers>
        <firstName>Michael</firstName>
        <isOriginalCosponsor>False</isOriginalCosponsor>
        <fullName>Rep. Fitzpatrick, Michael G. [R-PA-8]</fullName>
        <sponsorshipDate>2016-06-14</sponsorshipDate>
        <district>8</district>
        <middleName>G.</middleName>
        <sponsorshipWithdrawnDate />
        <lastName>Fitzpatrick</lastName>
        <bioguideId>F000451</bioguideId>
        <party>R</party>
      </item>
      <item>
        <state>TX</state>
        <identifiers>
          <lisID>1487</lisID>
          <gpoId>8168</gpoId>
          <bioguideId>G000377</bioguideId>
        </identifiers>
        <firstName>KAY</firstName>
        <isOriginalCosponsor>False</isOriginalCosponsor>
        <fullName>Rep. Granger, Kay [R-TX-12]</fullName>
        <sponsorshipDate>2016-06-14</sponsorshipDate>
        <district>12</district>
        <middleName />
        <sponsorshipWithdrawnDate />
        <lastName>GRANGER</lastName>
        <bioguideId>G000377</bioguideId>
        <party>R</party>
      </item>
      <item>
        <state>OH</state>
        <identifiers>
          <lisID>2152</lisID>
          <bioguideId>W000815</bioguideId>
          <gpoId />
        </identifiers>
        <firstName>Brad</firstName>
        <isOriginalCosponsor>False</isOriginalCosponsor>
        <fullName>Rep. Wenstrup, Brad R. [R-OH-2]</fullName>
        <sponsorshipDate>2016-06-20</sponsorshipDate>
        <district>2</district>
        <middleName>R.</middleName>
        <sponsorshipWithdrawnDate />
        <lastName>Wenstrup</lastName>
        <bioguideId>W000815</bioguideId>
        <party>R</party>
      </item>
      <item>
        <state>TX</state>
        <identifiers>
          <lisID>2268</lisID>
          <bioguideId>R000601</bioguideId>
          <gpoId />
        </identifiers>
        <firstName>John</firstName>
        <isOriginalCosponsor>False</isOriginalCosponsor>
        <fullName>Rep. Ratcliffe, John [R-TX-4]</fullName>
        <sponsorshipDate>2016-06-22</sponsorshipDate>
        <district>4</district>
        <middleName />
        <sponsorshipWithdrawnDate />
        <lastName>Ratcliffe</lastName>
        <bioguideId>R000601</bioguideId>
        <party>R</party>
      </item>
      <item>
        <state>OH</state>
        <identifiers>
          <lisID>1664</lisID>
          <bioguideId>T000462</bioguideId>
          <gpoId>8102</gpoId>
        </identifiers>
        <firstName>PATRICK</firstName>
        <isOriginalCosponsor>False</isOriginalCosponsor>
        <fullName>Rep. Tiberi, Patrick J. [R-OH-12]</fullName>
        <sponsorshipDate>2016-07-01</sponsorshipDate>
        <district>12</district>
        <middleName>J.</middleName>
        <sponsorshipWithdrawnDate />
        <lastName>TIBERI</lastName>
        <bioguideId>T000462</bioguideId>
        <party>R</party>
      </item>
      <item>
        <state>AL</state>
        <identifiers>
          <lisID>1987</lisID>
          <gpoId>7790</gpoId>
          <bioguideId>B001274</bioguideId>
        </identifiers>
        <firstName>Mo</firstName>
        <isOriginalCosponsor>False</isOriginalCosponsor>
        <fullName>Rep. Brooks, Mo [R-AL-5]</fullName>
        <sponsorshipDate>2016-07-01</sponsorshipDate>
        <district>5</district>
        <middleName />
        <sponsorshipWithdrawnDate />
        <lastName>Brooks</lastName>
        <bioguideId>B001274</bioguideId>
        <party>R</party>
      </item>
      <item>
        <state>KY</state>
        <identifiers>
          <lisID>977</lisID>
          <gpoId>7957</gpoId>
          <bioguideId>R000395</bioguideId>
        </identifiers>
        <firstName>HAROLD</firstName>
        <isOriginalCosponsor>False</isOriginalCosponsor>
        <fullName>Rep. Rogers, Harold [R-KY-5]</fullName>
        <sponsorshipDate>2016-07-01</sponsorshipDate>
        <district>5</district>
        <middleName />
        <sponsorshipWithdrawnDate />
        <lastName>ROGERS</lastName>
        <bioguideId>R000395</bioguideId>
        <party>R</party>
      </item>
      <item>
        <state>MI</state>
        <identifiers>
          <lisID>2250</lisID>
          <gpoId />
          <bioguideId>T000475</bioguideId>
        </identifiers>
        <firstName>David</firstName>
        <isOriginalCosponsor>False</isOriginalCosponsor>
        <fullName>Rep. Trott, David A. [R-MI-11]</fullName>
        <sponsorshipDate>2016-07-01</sponsorshipDate>
        <district>11</district>
        <middleName>A.</middleName>
        <sponsorshipWithdrawnDate />
        <lastName>Trott</lastName>
        <bioguideId>T000475</bioguideId>
        <party>R</party>
      </item>
      <item>
        <state>LA</state>
        <identifiers>
          <lisID>2245</lisID>
          <gpoId />
          <bioguideId>G000577</bioguideId>
        </identifiers>
        <firstName>Garret</firstName>
        <isOriginalCosponsor>False</isOriginalCosponsor>
        <fullName>Rep. Graves, Garret [R-LA-6]</fullName>
        <sponsorshipDate>2016-07-06</sponsorshipDate>
        <district>6</district>
        <middleName />
        <sponsorshipWithdrawnDate />
        <lastName>Graves</lastName>
        <bioguideId>G000577</bioguideId>
        <party>R</party>
      </item>
      <item>
        <state>LA</state>
        <identifiers>
          <lisID>1787</lisID>
          <bioguideId>B001255</bioguideId>
          <gpoId>7965</gpoId>
        </identifiers>
        <firstName>Charles</firstName>
        <isOriginalCosponsor>False</isOriginalCosponsor>
        <fullName>Rep. Boustany, Charles W., Jr. [R-LA-3]</fullName>
        <sponsorshipDate>2016-07-12</sponsorshipDate>
        <district>3</district>
        <middleName>W.</middleName>
        <sponsorshipWithdrawnDate />
        <lastName>Boustany</lastName>
        <bioguideId>B001255</bioguideId>
        <party>R</party>
      </item>
      <item>
        <state>KY</state>
        <identifiers>
          <lisID>1922</lisID>
          <bioguideId>G000558</bioguideId>
          <gpoId>7954</gpoId>
        </identifiers>
        <firstName>Brett</firstName>
        <isOriginalCosponsor>False</isOriginalCosponsor>
        <fullName>Rep. Guthrie, Brett [R-KY-2]</fullName>
        <sponsorshipDate>2016-07-13</sponsorshipDate>
        <district>2</district>
        <middleName />
        <sponsorshipWithdrawnDate />
        <lastName>Guthrie</lastName>
        <bioguideId>G000558</bioguideId>
        <party>R</party>
      </item>
      <item>
        <state>AZ</state>
        <identifiers>
          <lisID>1992</lisID>
          <gpoId>7798</gpoId>
          <bioguideId>G000565</bioguideId>
        </identifiers>
        <firstName>Paul</firstName>
        <isOriginalCosponsor>False</isOriginalCosponsor>
        <fullName>Rep. Gosar, Paul A. [R-AZ-4]</fullName>
        <sponsorshipDate>2016-07-14</sponsorshipDate>
        <district>4</district>
        <middleName>A.</middleName>
        <sponsorshipWithdrawnDate />
        <lastName>Gosar</lastName>
        <bioguideId>G000565</bioguideId>
        <party>R</party>
      </item>
      <item>
        <state>AR</state>
        <identifiers>
          <lisID>2223</lisID>
          <bioguideId>H001072</bioguideId>
          <gpoId />
        </identifiers>
        <firstName>J.</firstName>
        <isOriginalCosponsor>False</isOriginalCosponsor>
        <fullName>Rep. Hill, J. French [R-AR-2]</fullName>
        <sponsorshipDate>2016-09-06</sponsorshipDate>
        <district>2</district>
        <middleName>French</middleName>
        <sponsorshipWithdrawnDate />
        <lastName>Hill</lastName>
        <bioguideId>H001072</bioguideId>
        <party>R</party>
      </item>
      <item>
        <state>OH</state>
        <identifiers>
          <lisID>2047</lisID>
          <bioguideId>S001187</bioguideId>
          <gpoId>8105</gpoId>
        </identifiers>
        <firstName>Steve</firstName>
        <isOriginalCosponsor>False</isOriginalCosponsor>
        <fullName>Rep. Stivers, Steve [R-OH-15]</fullName>
        <sponsorshipDate>2016-09-06</sponsorshipDate>
        <district>15</district>
        <middleName />
        <sponsorshipWithdrawnDate />
        <lastName>Stivers</lastName>
        <bioguideId>S001187</bioguideId>
        <party>R</party>
      </item>
      <item>
        <state>CA</state>
        <identifiers>
          <lisID>1909</lisID>
          <gpoId>7857</gpoId>
          <bioguideId>H001048</bioguideId>
        </identifiers>
        <firstName>Duncan</firstName>
        <isOriginalCosponsor>False</isOriginalCosponsor>
        <fullName>Rep. Hunter, Duncan D. [R-CA-50]</fullName>
        <sponsorshipDate>2016-09-06</sponsorshipDate>
        <district>50</district>
        <middleName>D.</middleName>
        <sponsorshipWithdrawnDate />
        <lastName>Hunter</lastName>
        <bioguideId>H001048</bioguideId>
        <party>R</party>
      </item>
      <item>
        <state>KY</state>
        <identifiers>
          <lisID>2131</lisID>
          <bioguideId>B001282</bioguideId>
          <gpoId />
        </identifiers>
        <firstName>Andy</firstName>
        <isOriginalCosponsor>False</isOriginalCosponsor>
        <fullName>Rep. Barr, Andy [R-KY-6]</fullName>
        <sponsorshipDate>2016-09-12</sponsorshipDate>
        <district>6</district>
        <middleName />
        <sponsorshipWithdrawnDate />
        <lastName>Barr</lastName>
        <bioguideId>B001282</bioguideId>
        <party>R</party>
      </item>
      <item>
        <state>CA</state>
        <identifiers>
          <lisID>2100</lisID>
          <gpoId />
          <bioguideId>L000578</bioguideId>
        </identifiers>
        <firstName>Doug</firstName>
        <isOriginalCosponsor>False</isOriginalCosponsor>
        <fullName>Rep. LaMalfa, Doug [R-CA-1]</fullName>
        <sponsorshipDate>2016-09-20</sponsorshipDate>
        <district>1</district>
        <middleName />
        <sponsorshipWithdrawnDate />
        <lastName>LaMalfa</lastName>
        <bioguideId>L000578</bioguideId>
        <party>R</party>
      </item>
      <item>
        <state>TN</state>
        <identifiers>
          <lisID>1748</lisID>
          <gpoId>8154</gpoId>
          <bioguideId>B001243</bioguideId>
        </identifiers>
        <firstName>Marsha</firstName>
        <isOriginalCosponsor>False</isOriginalCosponsor>
        <fullName>Rep. Blackburn, Marsha [R-TN-7]</fullName>
        <sponsorshipDate>2016-09-26</sponsorshipDate>
        <district>7</district>
        <middleName />
        <sponsorshipWithdrawnDate />
        <lastName>Blackburn</lastName>
        <bioguideId>B001243</bioguideId>
        <party>R</party>
      </item>
    </cosponsors>
    <committees>
      <billCommittees>
        <item>
          <activities>
            <item>
              <name>Markup by</name>
              <date>2016-07-07T14:08:29Z</date>
            </item>
            <item>
              <name>Referred to</name>
              <date>2015-10-20T16:01:35Z</date>
            </item>
          </activities>
          <systemCode>hsju00</systemCode>
          <type>Standing</type>
          <subcommittees>
            <item>
              <name>Constitution and Civil Justice Subcommittee</name>
              <systemCode>hsju10</systemCode>
              <activities>
                <item>
                  <name>Discharged from</name>
                  <date>2016-07-05T14:06:33Z</date>
                </item>
                <item>
                  <name>Referred to</name>
                  <date>2015-11-03T18:40:17Z</date>
                </item>
              </activities>
            </item>
          </subcommittees>
          <chamber>House</chamber>
          <name>Judiciary Committee</name>
        </item>
      </billCommittees>
    </committees>
    <constitutionalAuthorityStatementText><![CDATA[<pre>From the Congressional Record Online through the Government Publishing Office [<a href='http://www.gpo.gov'>www.gpo.gov</a>]By Mr. POE of Texas:H.R. 3765.Congress has the power to enact this legislation pursuantto the following:Article I, Section 8, Clause 18[Page H7027]</pre>]]></constitutionalAuthorityStatementText>
  </bill>
  <dublinCore xmlns:dc="http://purl.org/dc/elements/1.1/">
    <dc:format>text/xml</dc:format>
    <dc:language>EN</dc:language>
    <dc:rights>Pursuant to Title 17 Section 105 of the United States Code, this file is not subject to copyright protection and is in the public domain.</dc:rights>
    <dc:contributor>Congressional Research Service, Library of Congress</dc:contributor>
    <dc:description>This file contains bill summaries and statuses for federal legislation. A bill summary describes the most significant provisions of a piece of legislation and details the effects the legislative text may have on current law and federal programs. Bill summaries are authored by the Congressional Research Service (CRS) of the Library of Congress. As stated in Public Law 91-510 (2 USC 166 (d)(6)), one of the duties of CRS is "to prepare summaries and digests of bills and resolutions of a public general nature introduced in the Senate or House of Representatives". For more information, refer to the User Guide that accompanies this file.</dc:description>
  </dublinCore>
</billStatus>

