<?xml version="1.0" encoding="UTF-8"?>
<billStatus>
  <bill>
    <billNumber>1938</billNumber>
    <billType>S</billType>
    <summaries>
      <billSummaries>
        <item>
          <actionDate>2015-08-05</actionDate>
          <actionDesc>Introduced in Senate</actionDesc>
          <text><![CDATA[<p><strong>Career-Ready Student Veterans Act</strong> <strong>of 2015</strong></p> <p>This bill adds the following new criteria for state approval, for the Department of Veterans Affairs (VA) educational assistance, of applications of educational institutions providing veterans with non-accredited courses: </p> <ul> <li>any program designed to prepare an individual for state licensure or certification must meet state instructional curriculum licensure or certification requirements, and </li> <li>any program designed to prepare an individual for employment pursuant to standards developed by a state board or agency in an occupation requiring approval or licensure must be approved or licensed by that state board or agency.</li> </ul> <p>The VA may waive either of these two requirements if: </p> <ul> <li>the educational institution is accredited by an agency or association recognized by the Secretary of Education; </li> <li>the program did not meet the requirements at any time during the two-year period preceding the waiver date; </li> <li>the waiver furthers the purposes of the educational assistance programs or would further the education interests of individuals eligible for assistance under such programs; and </li> <li>the educational institution does not provide any incentive payment based on securing enrollments or financial aid to any persons or entities engaged in student recruiting or admission activities or in making decisions regarding the award of student financial assistance, except for recruitment of foreign students residing in foreign countries who are ineligible for federal student assistance.</li> </ul> <p>The criteria added by this Act also apply to approval of accredited courses at for-profit educational institutions.</p> <p> The VA shall disapprove a course of education added by this Act unless the educational institution providing the course publicly discloses any conditions or additional requirements, including training, experience, or exams, required to obtain the license, certification, or approval for which the course of education is designed to provide preparation.</p>]]></text>
          <name>Introduced in Senate</name>
          <versionCode>00</versionCode>
          <lastSummaryUpdateDate>2015-09-04T21:04:48Z</lastSummaryUpdateDate>
          <updateDate>2015-08-05T04:00:00Z</updateDate>
        </item>
      </billSummaries>
    </summaries>
    <sponsors>
      <item>
        <state>CT</state>
        <middleName />
        <byRequestType />
        <firstName>Richard</firstName>
        <lastName>Blumenthal</lastName>
        <identifiers>
          <lisID>2076</lisID>
          <gpoId>8332</gpoId>
          <bioguideId>B001277</bioguideId>
        </identifiers>
        <bioguideId>B001277</bioguideId>
        <party>D</party>
        <fullName>Sen. Blumenthal, Richard [D-CT]</fullName>
      </item>
    </sponsors>
    <subjects>
      <billSubjects>
        <legislativeSubjects>
          <item>
            <name>Higher education</name>
          </item>
          <item>
            <name>Licensing and registrations</name>
          </item>
          <item>
            <name>Student aid and college costs</name>
          </item>
          <item>
            <name>Teaching, teachers, curricula</name>
          </item>
          <item>
            <name>Veterans' education, employment, rehabilitation</name>
          </item>
        </legislativeSubjects>
        <policyArea>
          <name>Armed Forces and National Security</name>
        </policyArea>
      </billSubjects>
    </subjects>
    <cosponsors>
      <item>
        <identifiers>
          <bioguideId>T000476</bioguideId>
          <gpoId />
          <lisID>2291</lisID>
        </identifiers>
        <firstName>Thomas</firstName>
        <party>R</party>
        <bioguideId>T000476</bioguideId>
        <fullName>Sen. Tillis, Thom [R-NC]</fullName>
        <isOriginalCosponsor>True</isOriginalCosponsor>
        <state>NC</state>
        <middleName>Roland</middleName>
        <sponsorshipWithdrawnDate />
        <sponsorshipDate>2015-08-05</sponsorshipDate>
        <lastName>Tillis</lastName>
      </item>
      <item>
        <identifiers>
          <lisID>136</lisID>
          <bioguideId>B000944</bioguideId>
          <gpoId>8309</gpoId>
        </identifiers>
        <firstName>SHERROD</firstName>
        <party>D</party>
        <bioguideId>B000944</bioguideId>
        <fullName>Sen. Brown, Sherrod [D-OH]</fullName>
        <isOriginalCosponsor>True</isOriginalCosponsor>
        <state>OH</state>
        <middleName />
        <sponsorshipWithdrawnDate />
        <sponsorshipDate>2015-08-05</sponsorshipDate>
        <lastName>BROWN</lastName>
      </item>
      <item>
        <identifiers>
          <lisID>179</lisID>
          <gpoId>8283</gpoId>
          <bioguideId>C000174</bioguideId>
        </identifiers>
        <firstName>THOMAS</firstName>
        <party>D</party>
        <bioguideId>C000174</bioguideId>
        <fullName>Sen. Carper, Thomas R. [D-DE]</fullName>
        <isOriginalCosponsor>True</isOriginalCosponsor>
        <state>DE</state>
        <middleName>R.</middleName>
        <sponsorshipWithdrawnDate />
        <sponsorshipDate>2015-08-05</sponsorshipDate>
        <lastName>CARPER</lastName>
      </item>
      <item>
        <identifiers>
          <bioguideId>C001075</bioguideId>
          <gpoId>7964</gpoId>
          <lisID>1925</lisID>
        </identifiers>
        <firstName>Bill</firstName>
        <party>R</party>
        <bioguideId>C001075</bioguideId>
        <fullName>Sen. Cassidy, Bill [R-LA]</fullName>
        <isOriginalCosponsor>True</isOriginalCosponsor>
        <state>LA</state>
        <middleName />
        <sponsorshipWithdrawnDate />
        <sponsorshipDate>2015-08-05</sponsorshipDate>
        <lastName>Cassidy</lastName>
      </item>
      <item>
        <identifiers>
          <lisID>1984</lisID>
          <gpoId>8297</gpoId>
          <bioguideId>C001088</bioguideId>
        </identifiers>
        <firstName>Christopher</firstName>
        <party>D</party>
        <bioguideId>C001088</bioguideId>
        <fullName>Sen. Coons, Christopher A. [D-DE]</fullName>
        <isOriginalCosponsor>True</isOriginalCosponsor>
        <state>DE</state>
        <middleName>A.</middleName>
        <sponsorshipWithdrawnDate />
        <sponsorshipDate>2015-08-05</sponsorshipDate>
        <lastName>Coons</lastName>
      </item>
      <item>
        <identifiers>
          <gpoId>8326</gpoId>
          <bioguideId>D000563</bioguideId>
          <lisID>326</lisID>
        </identifiers>
        <firstName>RICHARD</firstName>
        <party>D</party>
        <bioguideId>D000563</bioguideId>
        <fullName>Sen. Durbin, Richard J. [D-IL]</fullName>
        <isOriginalCosponsor>True</isOriginalCosponsor>
        <state>IL</state>
        <middleName>J.</middleName>
        <sponsorshipWithdrawnDate />
        <sponsorshipDate>2015-08-05</sponsorshipDate>
        <lastName>DURBIN</lastName>
      </item>
      <item>
        <identifiers>
          <bioguideId>F000062</bioguideId>
          <gpoId>8338</gpoId>
          <lisID>1332</lisID>
        </identifiers>
        <firstName>DIANNE</firstName>
        <party>D</party>
        <bioguideId>F000062</bioguideId>
        <fullName>Sen. Feinstein, Dianne [D-CA]</fullName>
        <isOriginalCosponsor>True</isOriginalCosponsor>
        <state>CA</state>
        <middleName />
        <sponsorshipWithdrawnDate />
        <sponsorshipDate>2015-08-05</sponsorshipDate>
        <lastName>FEINSTEIN</lastName>
      </item>
      <item>
        <identifiers>
          <gpoId>8336</gpoId>
          <bioguideId>G000555</bioguideId>
          <lisID>1866</lisID>
        </identifiers>
        <firstName>Kirsten</firstName>
        <party>D</party>
        <bioguideId>G000555</bioguideId>
        <fullName>Sen. Gillibrand, Kirsten E. [D-NY]</fullName>
        <isOriginalCosponsor>True</isOriginalCosponsor>
        <state>NY</state>
        <middleName>E.</middleName>
        <sponsorshipWithdrawnDate />
        <sponsorshipDate>2015-08-05</sponsorshipDate>
        <lastName>Gillibrand</lastName>
      </item>
      <item>
        <identifiers>
          <gpoId>8238</gpoId>
          <bioguideId>M001176</bioguideId>
          <lisID>1900</lisID>
        </identifiers>
        <firstName>Jeff</firstName>
        <party>D</party>
        <bioguideId>M001176</bioguideId>
        <fullName>Sen. Merkley, Jeff [D-OR]</fullName>
        <isOriginalCosponsor>True</isOriginalCosponsor>
        <state>OR</state>
        <middleName />
        <sponsorshipWithdrawnDate />
        <sponsorshipDate>2015-08-05</sponsorshipDate>
        <lastName>Merkley</lastName>
      </item>
      <item>
        <identifiers>
          <lisID>1837</lisID>
          <bioguideId>M001169</bioguideId>
          <gpoId>7870</gpoId>
        </identifiers>
        <firstName>Christopher</firstName>
        <party>D</party>
        <bioguideId>M001169</bioguideId>
        <fullName>Sen. Murphy, Christopher [D-CT]</fullName>
        <isOriginalCosponsor>True</isOriginalCosponsor>
        <state>CT</state>
        <middleName />
        <sponsorshipWithdrawnDate />
        <sponsorshipDate>2015-08-05</sponsorshipDate>
        <lastName>Murphy</lastName>
      </item>
      <item>
        <identifiers>
          <gpoId>8272</gpoId>
          <bioguideId>R000122</bioguideId>
          <lisID>949</lisID>
        </identifiers>
        <firstName>JOHN</firstName>
        <party>D</party>
        <bioguideId>R000122</bioguideId>
        <fullName>Sen. Reed, Jack [D-RI]</fullName>
        <isOriginalCosponsor>True</isOriginalCosponsor>
        <state>RI</state>
        <middleName>F.</middleName>
        <sponsorshipWithdrawnDate />
        <sponsorshipDate>2015-08-05</sponsorshipDate>
        <lastName>REED</lastName>
      </item>
      <item>
        <identifiers>
          <lisID>1036</lisID>
          <gpoId>8279</gpoId>
          <bioguideId>S000148</bioguideId>
        </identifiers>
        <firstName>CHARLES</firstName>
        <party>D</party>
        <bioguideId>S000148</bioguideId>
        <fullName>Sen. Schumer, Charles E. [D-NY]</fullName>
        <isOriginalCosponsor>True</isOriginalCosponsor>
        <state>NY</state>
        <middleName>E.</middleName>
        <sponsorshipWithdrawnDate />
        <sponsorshipDate>2015-08-05</sponsorshipDate>
        <lastName>SCHUMER</lastName>
      </item>
      <item>
        <identifiers>
          <gpoId>8276</gpoId>
          <bioguideId>S001181</bioguideId>
          <lisID>1901</lisID>
        </identifiers>
        <firstName>Jeanne</firstName>
        <party>D</party>
        <bioguideId>S001181</bioguideId>
        <fullName>Sen. Shaheen, Jeanne [D-NH]</fullName>
        <isOriginalCosponsor>True</isOriginalCosponsor>
        <state>NH</state>
        <middleName />
        <sponsorshipWithdrawnDate />
        <sponsorshipDate>2015-08-05</sponsorshipDate>
        <lastName>Shaheen</lastName>
      </item>
      <item>
        <identifiers>
          <lisID>2182</lisID>
          <bioguideId>W000817</bioguideId>
          <gpoId />
        </identifiers>
        <firstName>Elizabeth</firstName>
        <party>D</party>
        <bioguideId>W000817</bioguideId>
        <fullName>Sen. Warren, Elizabeth [D-MA]</fullName>
        <isOriginalCosponsor>False</isOriginalCosponsor>
        <state>MA</state>
        <middleName>A.</middleName>
        <sponsorshipWithdrawnDate />
        <sponsorshipDate>2015-09-16</sponsorshipDate>
        <lastName>Warren</lastName>
      </item>
    </cosponsors>
    <cboCostEstimates />
    <congress>114</congress>
    <calendarNumbers />
    <latestAction>
      <links />
      <text>Committee on Veterans' Affairs. Hearings held.</text>
      <actionDate>2015-09-16</actionDate>
    </latestAction>
    <notes />
    <introducedDate>2015-08-05</introducedDate>
    <createDate>2015-08-06T08:30:20Z</createDate>
    <titles>
      <item>
        <titleType>Short Titles as Introduced</titleType>
        <parentTitleType />
        <title>Career-Ready Student Veterans Act of 2015</title>
        <chamberCode />
        <chamberName />
      </item>
      <item>
        <titleType>Official Title as Introduced</titleType>
        <parentTitleType />
        <title>A bill to amend title 38, United States Code, to improve the approval of certain programs of education for purposes of educational assistance provided by the Department of Veterans Affairs, and for other purposes.</title>
        <chamberCode />
        <chamberName />
      </item>
      <item>
        <titleType>Display Title</titleType>
        <parentTitleType />
        <title>Career-Ready Student Veterans Act of 2015</title>
        <chamberCode />
        <chamberName />
      </item>
    </titles>
    <version>1.0.0</version>
    <title>Career-Ready Student Veterans Act of 2015</title>
    <committeeReports />
    <committees>
      <billCommittees>
        <item>
          <chamber>Senate</chamber>
          <type>Standing</type>
          <name>Veterans' Affairs Committee</name>
          <systemCode>ssva00</systemCode>
          <subcommittees />
          <activities>
            <item>
              <name>Hearings by</name>
              <date>2015-09-16T18:30:00Z</date>
            </item>
            <item>
              <name>Referred to</name>
              <date>2015-08-05T14:24:29Z</date>
            </item>
          </activities>
        </item>
      </billCommittees>
    </committees>
    <recordedVotes />
    <laws />
    <actions>
      <actionTypeCounts>
        <referredToCommittee>1</referredToCommittee>
        <introducedInSenate>1</introducedInSenate>
        <hearingsHeld>1</hearingsHeld>
      </actionTypeCounts>
      <item>
        <actionDate>2015-09-16</actionDate>
        <committee>
          <name>Veterans' Affairs Committee</name>
          <systemCode>ssva00</systemCode>
        </committee>
        <links />
        <sourceSystem>
          <name>Senate</name>
          <code>0</code>
        </sourceSystem>
        <text>Committee on Veterans' Affairs. Hearings held.</text>
        <type>Committee</type>
      </item>
      <item>
        <actionDate>2015-08-05</actionDate>
        <committee>
          <name>Veterans' Affairs Committee</name>
          <systemCode>ssva00</systemCode>
        </committee>
        <links />
        <sourceSystem>
          <name>Senate</name>
          <code>0</code>
        </sourceSystem>
        <text>Read twice and referred to the Committee on Veterans' Affairs.</text>
        <type>IntroReferral</type>
      </item>
      <item>
        <committee />
        <text>Introduced in Senate</text>
        <type>IntroReferral</type>
        <links />
        <actionCode>10000</actionCode>
        <sourceSystem>
          <name>Library of Congress</name>
          <code>9</code>
        </sourceSystem>
        <actionDate>2015-08-05</actionDate>
      </item>
      <actionByCounts>
        <senate>3</senate>
      </actionByCounts>
    </actions>
    <policyArea>
      <name>Armed Forces and National Security</name>
    </policyArea>
    <amendments />
    <updateDate>2017-06-02T23:18:55Z</updateDate>
    <originChamber>Senate</originChamber>
    <relatedBills>
      <item>
        <congress>114</congress>
        <latestAction>
          <actionDate>2016-02-10</actionDate>
          <text>Received in the Senate and Read twice and referred to the Committee on Veterans' Affairs.</text>
        </latestAction>
        <latestTitle>Career-Ready Student Veterans Act</latestTitle>
        <relationshipDetails>
          <item>
            <type>Related bill</type>
            <identifiedBy>CRS</identifiedBy>
          </item>
        </relationshipDetails>
        <number>2360</number>
        <type>HR</type>
      </item>
      <item>
        <congress>114</congress>
        <latestAction>
          <actionDate>2016-05-16</actionDate>
          <text>Placed on Senate Legislative Calendar under General Orders. Calendar No. 467.</text>
        </latestAction>
        <latestTitle>Veterans First Act</latestTitle>
        <relationshipDetails>
          <item>
            <type>Related bill</type>
            <identifiedBy>CRS</identifiedBy>
          </item>
        </relationshipDetails>
        <number>2921</number>
        <type>S</type>
      </item>
      <item>
        <congress>114</congress>
        <latestAction>
          <actionDate>2016-10-19</actionDate>
          <text>Referred to the Subcommittee on Military Personnel.</text>
        </latestAction>
        <latestTitle>SERVICE Act</latestTitle>
        <relationshipDetails>
          <item>
            <type>Related bill</type>
            <identifiedBy>CRS</identifiedBy>
          </item>
        </relationshipDetails>
        <number>6062</number>
        <type>HR</type>
      </item>
    </relatedBills>
  </bill>
  <dublinCore xmlns:dc="http://purl.org/dc/elements/1.1/">
    <dc:format>text/xml</dc:format>
    <dc:language>EN</dc:language>
    <dc:rights>Pursuant to Title 17 Section 105 of the United States Code, this file is not subject to copyright protection and is in the public domain.</dc:rights>
    <dc:contributor>Congressional Research Service, Library of Congress</dc:contributor>
    <dc:description>This file contains bill summaries and statuses for federal legislation. A bill summary describes the most significant provisions of a piece of legislation and details the effects the legislative text may have on current law and federal programs. Bill summaries are authored by the Congressional Research Service (CRS) of the Library of Congress. As stated in Public Law 91-510 (2 USC 166 (d)(6)), one of the duties of CRS is "to prepare summaries and digests of bills and resolutions of a public general nature introduced in the Senate or House of Representatives". For more information, refer to the User Guide that accompanies this file.</dc:description>
  </dublinCore>
</billStatus>

